{
  "light_offset": {
    "gray": [700, 800, 900],
    "night": [700, 800, 900],
    "sky": [700, 800, 900],
    "sea": [500, 600, 700],
    "blue": [500, 600, 700],
    "teal": [600, 700, 800],
    "green": [500, 600, 700],
    "yellow": [700, 800, 900],
    "orange": [600, 700, 800],
    "red": [500, 600, 700],
    "rose": [600, 700, 800],
    "pink": [600, 700, 800],
    "purple": [700, 800, 900]
  },
  "dark_offset": {
    "gray": [300, 200, 100],
    "night": [300, 200, 100],
    "sky": [400, 300, 200],
    "sea": [300, 200, 100],
    "blue": [400, 300, 200],
    "teal": [400, 300, 200],
    "green": [300, 200, 100],
    "yellow": [400, 300, 200],
    "orange": [400, 300, 200],
    "red": [400, 300, 200],
    "rose": [300, 200, 100],
    "pink": [400, 300, 200],
    "purple": [400, 300, 200]
  }
}
